galsim_hub/__init__.py
galsim_hub/generative_model.py
galsim_hub/input_generative.py
galsim_hub-0.0.1rc2.dist-info/LICENSE
galsim_hub-0.0.1rc2.dist-info/METADATA
galsim_hub-0.0.1rc2.dist-info/WHEEL
galsim_hub-0.0.1rc2.dist-info/top_level.txt
galsim_hub-0.0.1rc2.dist-info/RECORD
